{
  "users": [
    {
      "id": "63a0",
      "userName": "ssssss_55",
      "userEmail": "aaaaaaa@as.am",
      "phone": "+37477945734",
      "age": "1"
    },
    {
      "id": "7e97",
      "userName": "ssssss_55",
      "userEmail": "aaaaaaa@as.am",
      "phone": "+37477945734",
      "age": "1"
    },
    {
      "id": "3a4d",
      "userName": "ssssss_55",
      "userEmail": "armen@hmail.com",
      "phone": "+37477945734",
      "age": 24
    },
    {
      "id": "8072",
      "userName": "ssssss_55",
      "userEmail": "armen@hmail.com",
      "phone": "+37477945734",
      "age": 24
    },
    {
      "id": "56e2",
      "userName": "ssssss_55",
      "userEmail": "armen@hmail.com",
      "phone": "+37477945734",
      "age": 24
    },
    {
      "id": "ba5a",
      "userName": "ssssss_55",
      "userEmail": "armen@hmail.com",
      "phone": "+37477945734",
      "age": 24
    },
    {
      "id": "2efa",
      "userName": "ssssss_55",
      "userEmail": "armen@hmail.com",
      "phone": "+37477945734",
      "age": 24
    },
    {
      "id": "1242",
      "userName": "ssssss_55",
      "userEmail": "armen@hmail.com",
      "phone": "+37477945734",
      "age": 24
    },
    {
      "id": "73fd",
      "userName": "ssssss_55",
      "userEmail": "armen@hmail.com",
      "phone": "+37477945734",
      "age": 24
    },
    {
      "id": "2e52",
      "userName": "ssssss_55",
      "userEmail": "armen@hmail.com",
      "phone": "+37477945734",
      "age": 24
    },
    {
      "id": "8c33",
      "userName": "aaaaaaaA",
      "userEmail": "aaaaaaa@as.am",
      "phone": "+37477945734",
      "age": 8
    },
    {
      "id": "515a",
      "userName": "aaaaaaaA",
      "userEmail": "aaaaaaa@as.am",
      "phone": "+37477945734",
      "age": 4
    },
    {
      "id": "23c1",
      "userName": "aaaaaaaA",
      "userEmail": "aaaaaaa@as.am",
      "phone": "+37477945734",
      "age": 4
    },
    {
      "id": "06a7",
      "userName": "aaaaaaaA",
      "userEmail": "aaaaaaa@as.am",
      "phone": "+37477945734",
      "age": 4
    },
    {
      "id": "ca7e",
      "userName": "aaaaaaaA",
      "userEmail": "aaaaaaa@as.am",
      "phone": "+37477945734",
      "age": 4
    }
  ]
}